Metadata-Version: 2.1
Name: ligandistributions
Version: 0.1
Summary: Gaussian distributions
License: UNKNOWN
Platform: UNKNOWN
